logging_strict/__init__.py
logging_strict/__init__.pyi
logging_strict/_version.py
logging_strict/_version.pyi
logging_strict/constants.py
logging_strict/constants.pyi
logging_strict/ep_validate_yaml.py
logging_strict/ep_validate_yaml.pyi
logging_strict/exceptions.py
logging_strict/exceptions.pyi
logging_strict/logging_api.py
logging_strict/logging_api.pyi
logging_strict/logging_api_test.py
logging_strict/logging_api_test.pyi
logging_strict/logging_strict.yml
logging_strict/logging_yaml_abc.py
logging_strict/logging_yaml_abc.pyi
logging_strict/logging_yaml_validate.py
logging_strict/logging_yaml_validate.pyi
logging_strict/py.typed
logging_strict/register_config.py
logging_strict/register_config.pyi
logging_strict/version_semantic.py
logging_strict/version_semantic.pyi
logging_strict/bad_idea/__init__.py
logging_strict/bad_idea/folder0/__init__.py
logging_strict/bad_idea/folder0/mp_1_shared.worker.logging.config.yaml
logging_strict/bad_idea/folder1/__init__.py
logging_strict/bad_idea/folder1/mp_1_shared.worker.logging.config.yaml
logging_strict/configs/__init__.py
logging_strict/configs/mp_1_asz.worker.logging.config.yaml
logging_strict/configs/textual_1_asz.app.logging.config.yaml
logging_strict/tech_niques/__init__.py
logging_strict/tech_niques/__init__.pyi
logging_strict/tech_niques/context_locals.py
logging_strict/tech_niques/context_locals.pyi
logging_strict/tech_niques/coverage_misbehaves.py
logging_strict/tech_niques/coverage_misbehaves.pyi
logging_strict/tech_niques/logger_redirect.py
logging_strict/tech_niques/logger_redirect.pyi
logging_strict/tech_niques/logging_capture.py
logging_strict/tech_niques/logging_capture.pyi
logging_strict/tech_niques/stream_capture.py
logging_strict/tech_niques/stream_capture.pyi
logging_strict/util/__init__.py
logging_strict/util/check_logging.py
logging_strict/util/check_logging.pyi
logging_strict/util/check_type.py
logging_strict/util/check_type.pyi
logging_strict/util/package_resource.py
logging_strict-1.6.1.dist-info/licenses/LICENSE.txt
logging_strict-1.6.1.dist-info/licenses/NOTICE.txt
logging_strict-1.6.1.dist-info/METADATA
logging_strict-1.6.1.dist-info/WHEEL
logging_strict-1.6.1.dist-info/entry_points.txt
logging_strict-1.6.1.dist-info/top_level.txt
logging_strict-1.6.1.dist-info/RECORD
