Metadata-Version: 2.4
Name: logging-strict
Version: 1.6.1
Summary: logging.config yaml strict typing and editable
Author-email: Dave Faulkmore <faulkmore@protonmail.com>
Maintainer-email: Dave Faulkmore <faulkmore@protonmail.com>
License-Expression: Apache-2.0
Project-URL: Documentation, https://logging-strict.readthedocs.io/en/stable
Project-URL: Changes, https://raw.githubusercontent.com/msftcangoblowm/logging-strict/master/CHANGES.rst
Project-URL: PyPI Releases, https://pypi.org/project/logging-strict
Project-URL: Source code, https://github.com/msftcangoblowm/logging-strict
Project-URL: Issue tracker, https://github.com/msftcangoblowm/logging-strict/issues
Project-URL: Mastodon, https://mastodon.social/@msftcangoblowme
Keywords: strictyaml,pre-commit,yaml,logging.config
Classifier: Environment :: Console
Classifier: Development Status :: 4 - Beta
Classifier: Intended Audience :: Developers
Classifier: Operating System :: OS Independent
Classifier: Programming Language :: Python :: 3
Classifier: Programming Language :: Python :: 3.9
Classifier: Programming Language :: Python :: 3.10
Classifier: Programming Language :: Python :: 3.11
Classifier: Programming Language :: Python :: 3.12
Classifier: Programming Language :: Python :: 3.13
Classifier: Programming Language :: Python :: Implementation :: CPython
Classifier: Programming Language :: Python :: Implementation :: PyPy
Classifier: Topic :: System :: Logging
Classifier: Topic :: Software Development :: Testing
Classifier: Topic :: Software Development :: Quality Assurance
Classifier: Natural Language :: English
Classifier: Typing :: Typed
Requires-Python: >=3.9
License-File: LICENSE.txt
License-File: NOTICE.txt
Requires-Dist: appdirs
Requires-Dist: attrs
Requires-Dist: importlib-metadata
Requires-Dist: importlib-resources
Requires-Dist: python-dateutil>=2.9.0.post0
Requires-Dist: strictyaml
Requires-Dist: tomli; python_version < "3.11"
Requires-Dist: typing-extensions; python_version < "3.11"
Provides-Extra: pip
Requires-Dist: tomli==2.2.1; python_version < "3.11" and extra == "pip"
Requires-Dist: typing-extensions==4.12.2; python_version < "3.11" and extra == "pip"
Provides-Extra: pip-tools
Requires-Dist: click==8.2.0; extra == "pip-tools"
Requires-Dist: importlib-metadata==8.7.0; extra == "pip-tools"
Requires-Dist: packaging==25.0; extra == "pip-tools"
Requires-Dist: pip-tools==7.4.1; extra == "pip-tools"
Requires-Dist: pyproject-hooks==1.2.0; extra == "pip-tools"
Requires-Dist: tomli==2.2.1; python_version < "3.11" and extra == "pip-tools"
Requires-Dist: zipp==3.21.0; extra == "pip-tools"
Provides-Extra: dev
Requires-Dist: black==24.10.0; extra == "dev"
Requires-Dist: blackdoc==0.3.9; extra == "dev"
Requires-Dist: click==8.1.7; python_version < "3.10" and extra == "dev"
Requires-Dist: click==8.2.0; python_version >= "3.10" and extra == "dev"
Requires-Dist: coverage==7.6.10; extra == "dev"
Requires-Dist: fastjsonschema==2.21.1; extra == "dev"
Requires-Dist: flake8==7.1.1; extra == "dev"
Requires-Dist: flake8-pyproject==1.2.3; extra == "dev"
Requires-Dist: isort==5.13.2; extra == "dev"
Requires-Dist: markdown-it-py==3.0.0; extra == "dev"
Requires-Dist: mccabe==0.7.0; extra == "dev"
Requires-Dist: mdurl==0.1.2; extra == "dev"
Requires-Dist: more-itertools==10.6.0; extra == "dev"
Requires-Dist: mypy==1.15.0; extra == "dev"
Requires-Dist: mypy-extensions==1.0.0; extra == "dev"
Requires-Dist: packaging==25.0; extra == "dev"
Requires-Dist: pathspec==0.12.1; extra == "dev"
Requires-Dist: platformdirs==4.3.6; extra == "dev"
Requires-Dist: pycodestyle==2.12.1; extra == "dev"
Requires-Dist: pyflakes==3.2.0; extra == "dev"
Requires-Dist: pygments==2.19.1; extra == "dev"
Requires-Dist: rich==13.9.4; extra == "dev"
Requires-Dist: tomli==2.2.1; python_version < "3.11" and extra == "dev"
Requires-Dist: typing-extensions==4.12.2; python_version < "3.11" and extra == "dev"
Requires-Dist: validate-pyproject==0.24.1; extra == "dev"
Provides-Extra: manage
Requires-Dist: cfgv==3.4.0; extra == "manage"
Requires-Dist: distlib==0.3.9; extra == "manage"
Requires-Dist: filelock==3.16.1; extra == "manage"
Requires-Dist: identify==2.6.5; extra == "manage"
Requires-Dist: nodeenv==1.9.1; extra == "manage"
Requires-Dist: platformdirs==4.3.6; extra == "manage"
Requires-Dist: pre-commit==4.0.1; extra == "manage"
Requires-Dist: pyyaml==6.0.2; extra == "manage"
Requires-Dist: virtualenv==20.29.0; extra == "manage"
Provides-Extra: docs
Requires-Dist: aiologger==0.7.0; extra == "docs"
Requires-Dist: alabaster==1.0.0; extra == "docs"
Requires-Dist: anyio==4.8.0; extra == "docs"
Requires-Dist: attrs==24.2.0; extra == "docs"
Requires-Dist: babel==2.16.0; extra == "docs"
Requires-Dist: certifi==2025.4.26; extra == "docs"
Requires-Dist: charset-normalizer==3.4.2; extra == "docs"
Requires-Dist: click==8.2.0; extra == "docs"
Requires-Dist: click-log==0.4.0; extra == "docs"
Requires-Dist: colorama==0.4.6; extra == "docs"
Requires-Dist: docutils==0.21.2; extra == "docs"
Requires-Dist: dom-toml==2.0.0; extra == "docs"
Requires-Dist: domdf-python-tools==3.9.0; extra == "docs"
Requires-Dist: exceptiongroup==1.2.2; extra == "docs"
Requires-Dist: h11==0.14.0; extra == "docs"
Requires-Dist: idna==3.10; extra == "docs"
Requires-Dist: imagesize==1.4.1; extra == "docs"
Requires-Dist: jinja2==3.1.5; extra == "docs"
Requires-Dist: jsonschema==4.23.0; extra == "docs"
Requires-Dist: jsonschema-specifications==2024.10.1; extra == "docs"
Requires-Dist: markdown-it-py==3.0.0; extra == "docs"
Requires-Dist: markupsafe==3.0.2; extra == "docs"
Requires-Dist: mdit-py-plugins==0.4.2; extra == "docs"
Requires-Dist: mdurl==0.1.2; extra == "docs"
Requires-Dist: myst-parser==4.0.0; extra == "docs"
Requires-Dist: natsort==8.4.0; extra == "docs"
Requires-Dist: packaging==25.0; extra == "docs"
Requires-Dist: pygments==2.19.1; extra == "docs"
Requires-Dist: python-dateutil==2.9.0.post0; extra == "docs"
Requires-Dist: pyyaml==6.0.2; extra == "docs"
Requires-Dist: referencing==0.35.1; extra == "docs"
Requires-Dist: requests==2.32.3; extra == "docs"
Requires-Dist: rpds-py==0.22.3; extra == "docs"
Requires-Dist: scriv==1.5.1; extra == "docs"
Requires-Dist: six==1.17.0; extra == "docs"
Requires-Dist: sniffio==1.3.1; extra == "docs"
Requires-Dist: snowballstemmer==2.2.0; extra == "docs"
Requires-Dist: sphinx==8.1.3; extra == "docs"
Requires-Dist: sphinx-autobuild==2024.10.3; extra == "docs"
Requires-Dist: sphinx-external-toc-strict==2.0.3.post4; extra == "docs"
Requires-Dist: sphinx-paramlinks==0.6.0; extra == "docs"
Requires-Dist: sphinx-pyproject==0.3.0; extra == "docs"
Requires-Dist: sphinxcontrib-applehelp==2.0.0; extra == "docs"
Requires-Dist: sphinxcontrib-devhelp==2.0.0; extra == "docs"
Requires-Dist: sphinxcontrib-htmlhelp==2.1.0; extra == "docs"
Requires-Dist: sphinxcontrib-jsmath==1.0.1; extra == "docs"
Requires-Dist: sphinxcontrib-qthelp==2.0.0; extra == "docs"
Requires-Dist: sphinxcontrib-serializinghtml==2.0.0; extra == "docs"
Requires-Dist: sphobjinv==2.3.1.2; extra == "docs"
Requires-Dist: starlette==0.45.2; extra == "docs"
Requires-Dist: strictyaml==1.7.3; extra == "docs"
Requires-Dist: tomli==2.2.1; python_version < "3.11" and extra == "docs"
Requires-Dist: typing-extensions==4.12.2; extra == "docs"
Requires-Dist: urllib3==2.3.0; extra == "docs"
Requires-Dist: uvicorn==0.34.0; extra == "docs"
Requires-Dist: watchfiles==1.0.4; extra == "docs"
Requires-Dist: websockets==14.1; extra == "docs"
Dynamic: license-file
